sknni/__init__.py
sknni/cli.py
sknni/datasource/__init__.py
sknni/datasource/_npz_classification.py
sknni/internals/__init__.py
sknni/internals/_nni_config_generator.py
sknni/internals/_pipeline_builder.py
sknni/internals/_utils.py
scikit_nni-0.2.1.dist-info/LICENSE
scikit_nni-0.2.1.dist-info/METADATA
scikit_nni-0.2.1.dist-info/WHEEL
scikit_nni-0.2.1.dist-info/entry_points.txt
scikit_nni-0.2.1.dist-info/top_level.txt
scikit_nni-0.2.1.dist-info/RECORD
