Metadata-Version: 2.1
Name: scikit-nni
Version: 0.2.1
Summary: Hyper parameters search for scikit-learn components using Microsoft NNI
Home-page: https://github.com/ksachdeva/scikit-nni
Author: Kapil Sachdeva
Author-email: not@anemail.com
License: Apache Software License 2.0
Keywords: sknni,scikit-nni
Platform: UNKNOWN
Classifier: Development Status :: 2 - Pre-Alpha
Classifier: Intended Audience :: Developers
Classifier: License :: OSI Approved :: Apache Software License
Classifier: Natural Language :: English
Classifier: Programming Language :: Python :: 3.6
Classifier: Programming Language :: Python :: 3.7
Requires-Python: >=3.6, !=3.0.*, !=3.1.*, !=3.2.*, !=3.3.*, !=3.4.*, !=3.5.*
Requires-Dist: Click (>=7.0)
Requires-Dist: scikit-learn
Requires-Dist: nni
Requires-Dist: pymongo
Requires-Dist: absl-py
Requires-Dist: pyyaml
